ctfbridge/__init__.py
ctfbridge/factory.py
ctfbridge/py.typed
ctfbridge/base/__init__.py
ctfbridge/base/client.py
ctfbridge/base/identifier.py
ctfbridge/base/services/__init__.py
ctfbridge/base/services/attachment.py
ctfbridge/base/services/auth.py
ctfbridge/base/services/challenge.py
ctfbridge/base/services/scoreboard.py
ctfbridge/base/services/session.py
ctfbridge/cli/__init__.py
ctfbridge/cli/main.py
ctfbridge/cli/ui.py
ctfbridge/cli/commands/__init__.py
ctfbridge/cli/commands/cache.py
ctfbridge/cli/commands/platforms.py
ctfbridge/cli/commands/probe.py
ctfbridge/core/client.py
ctfbridge/core/http.py
ctfbridge/core/services/attachment.py
ctfbridge/core/services/auth.py
ctfbridge/core/services/challenge.py
ctfbridge/core/services/scoreboard.py
ctfbridge/core/services/session.py
ctfbridge/exceptions/__init__.py
ctfbridge/exceptions/attachment.py
ctfbridge/exceptions/auth.py
ctfbridge/exceptions/base.py
ctfbridge/exceptions/challenge.py
ctfbridge/exceptions/http.py
ctfbridge/exceptions/platform.py
ctfbridge/exceptions/scoreboard.py
ctfbridge/exceptions/session.py
ctfbridge/models/__init__.py
ctfbridge/models/auth.py
ctfbridge/models/capability.py
ctfbridge/models/challenge.py
ctfbridge/models/config.py
ctfbridge/models/error.py
ctfbridge/models/scoreboard.py
ctfbridge/models/submission.py
ctfbridge/models/user.py
ctfbridge/platforms/__init__.py
ctfbridge/platforms/detect.py
ctfbridge/platforms/registry.py
ctfbridge/platforms/berg/client.py
ctfbridge/platforms/berg/identifier.py
ctfbridge/platforms/berg/http/endpoints.py
ctfbridge/platforms/berg/models/challenge.py
ctfbridge/platforms/berg/services/challenge.py
ctfbridge/platforms/cryptohack/client.py
ctfbridge/platforms/cryptohack/identifier.py
ctfbridge/platforms/cryptohack/http/endpoints.py
ctfbridge/platforms/cryptohack/models/challenge.py
ctfbridge/platforms/cryptohack/services/auth.py
ctfbridge/platforms/cryptohack/services/challenge.py
ctfbridge/platforms/cryptohack/utils/csrf.py
ctfbridge-0.8.10.dist-info/licenses/LICENSE
ctfbridge-0.8.10.dist-info/METADATA
ctfbridge-0.8.10.dist-info/WHEEL
ctfbridge-0.8.10.dist-info/entry_points.txt
ctfbridge-0.8.10.dist-info/top_level.txt
ctfbridge-0.8.10.dist-info/RECORD
