Metadata-Version: 2.4
Name: ctfbridge
Version: 0.8.10
Summary: A Python library for interacting with multiple CTF platforms.
Author-email: bjornmorten <bjornmdev@proton.me>
License: MIT
Project-URL: Documentation, https://ctfbridge.readthedocs.io
Project-URL: Repository, https://github.com/bjornmorten/ctfbridge/
Project-URL: Issues, https://github.com/bjornmorten/ctfbridge/issues
Keywords: ctf
Classifier: Programming Language :: Python :: 3
Classifier: Programming Language :: Python :: 3.10
Classifier: Programming Language :: Python :: 3.11
Classifier: Programming Language :: Python :: 3.12
Classifier: License :: OSI Approved :: MIT License
Classifier: Operating System :: OS Independent
Requires-Python: <3.15,>=3.10
License-File: LICENSE
Requires-Dist: beautifulsoup4<5.0,>=4.9
Requires-Dist: pydantic<3.0,>=2.0
Requires-Dist: httpx>=0.28
Requires-Dist: asyncssh>=2.2.0
Requires-Dist: markdownify>=1.2.0
Provides-Extra: cli
Requires-Dist: typer[all]==0.20.0; extra == "cli"
Provides-Extra: dev
Requires-Dist: mypy; extra == "dev"
Requires-Dist: pytest; extra == "dev"
Requires-Dist: pytest-asyncio; extra == "dev"
Requires-Dist: pytest-mock; extra == "dev"
Requires-Dist: pytest-httpx; extra == "dev"
Requires-Dist: ruff; extra == "dev"
Requires-Dist: types-beautifulsoup4; extra == "dev"
Requires-Dist: pre-commit; extra == "dev"
Requires-Dist: twine; extra == "dev"
Requires-Dist: build; extra == "dev"
Provides-Extra: docs
Requires-Dist: mkdocs; extra == "docs"
Requires-Dist: mkdocs-material; extra == "docs"
Requires-Dist: mkdocstrings[python]; extra == "docs"
Requires-Dist: griffe-pydantic; extra == "docs"
Requires-Dist: pydantic; extra == "docs"
Requires-Dist: pymdown-extensions; extra == "docs"
Dynamic: license-file
